{
  "schema_version": "1.0",
  "policy_version": "1.0",
  "rubric_version": "1.0",
  "date": "2026-06-27",
  "generated_at": "2026-06-27T08:30:00+08:00",
  "status": "published",
  "run_report": {
    "candidates_scanned": 40,
    "published": 6,
    "dropped_safety": {
      "政治时政": 4,
      "纯新闻事件无梗壳": 12,
      "涉及具体人物无通用句式": 5,
      "涉及具体品牌公司": 2,
      "综艺节目主体内容": 1
    },
    "dropped_low_confidence": 5,
    "sources": [
      "weibo",
      "other"
    ],
    "evidence_summary": {
      "candidates_with_urls": 12,
      "platform_public_sources": 0,
      "aggregator_sources": 7,
      "search_media_sources": 14,
      "spillover_sources": 0,
      "dropped_insufficient_evidence": 2
    }
  },
  "items": [
    {
      "id": "2026-06-27-france-ac-abandon-eco",
      "title": "🌡️ 热到不提环保了",
      "aliases": [
        "法国人抢购空调",
        "极端高温打脸原则",
        "XX热到不提YY了"
      ],
      "platform": [
        "weibo",
        "other"
      ],
      "type": "句式梗",
      "summary": "法国今夏极端热浪（多地达45°C），此前80%民众认为空调「不环保」，如今大排长龙抢购；「热到不提环保了」成为「处境极端时原则让位于生存」的讽刺句式。",
      "origin": "2026年6月法国经历创纪录热浪，巴黎等多地突破45°C。此前调查显示84%法国人认为空调最有效，但78%视其为环境祸害；如今民众一早排队抢购，巴黎市长公开称家用空调是「一种祸害」却仍挡不住购买潮。百度实时热搜第18位（约628万热度），东方财富、杭州网、欧洲时报均有深度报道。",
      "usage": "「XX热到不提YY了」——任何处境极端到让人放弃原有立场的场景：项目截止日热到不提作息平衡了；天气热到不提防晒了直接跳进游泳池；延伸：「XX迫到不讲YY了」「所有信仰都有体感温度的上限」。评论区接龙：「原来原则是怕热的」。",
      "fun_point": "环保理想与生存现实的终极撕裂：「不用空调是我的信仰」vs「45°C，我跪了」。当最自称环保的人群第一批冲去超市抢购空调，梗的反差令人忍俊不禁——「原来信仰也有体感温度的上限」这句话可以装进所有「遇到真正困境时第一个放弃的那件事」。",
      "why_spread": "已验证：百度实时热搜第18位（约628万热度），东方财富、杭州网、欧洲时报均有深度报道；推测：极端天气时原则让位于生存的反差人人共鸣，「XX热到不提YY」句式可无限套用，法国人「死要面子活受罪」刻板印象加成传播笑感，跨文化话题吸引全球视野用户。",
      "lifecycle": "peak",
      "brand_usage": "家电/空调品牌可借「当原则遇到45°C」做产品文案；wellness品牌可用「别等热到忘了原则，提前备好」；内容账号可做「你为了什么放弃了自己的某个原则」互动；UGC话题：「你的哪条原则，遇到极端情况崩了」。",
      "risk": {
        "level": "safe",
        "note": "纯环保讽刺梗，不涉及具体政治人物或政策批评；引用法国民众行为时聚焦行为对比，不作道德评判。"
      },
      "score": 82,
      "days_on_list": 1,
      "published": true,
      "sources": [
        {
          "tier": "aggregator",
          "evidence_role": "popularity",
          "platform": "other",
          "url": "https://top.baidu.com/board?tab=realtime",
          "title": "百度热搜实时榜",
          "captured_at": "2026-06-27T08:00:00+08:00",
          "note": "百度实时热搜第18位「法国人热到不提环保了」（约628万热度），全国级传播热度确认"
        },
        {
          "tier": "search_media",
          "evidence_role": "origin",
          "platform": "other",
          "url": "https://finance.eastmoney.com/a/202606263783733310.html",
          "title": "45℃热浪！「空调」为何成法国政坛新「战场」",
          "captured_at": "2026-06-27T08:05:00+08:00",
          "note": "东方财富详述法国热浪中空调是否环保引发的政治争议，确认极端高温与环保立场反转的社会背景"
        },
        {
          "tier": "search_media",
          "evidence_role": "usage_context",
          "platform": "other",
          "url": "https://news.hangzhou.com.cn/gjxw/content/2026-06/26/content_9245949.htm",
          "title": "超40°C！法国人热到不提环保了，早起排队抢购空调",
          "captured_at": "2026-06-27T08:08:00+08:00",
          "note": "杭州网以梗名为题，记录法国民众排队抢购空调现场，与历史环保态度形成对比，确认梗化表达走红"
        },
        {
          "tier": "search_media",
          "evidence_role": "cross_platform",
          "platform": "other",
          "url": "https://www.oushinet.com/static/content/wechat/europeantimes/2026-06-26/1520051476033051969.html",
          "title": "法国热翻天，巴黎市长却警告：「家用空调是一种祸害」",
          "captured_at": "2026-06-27T08:10:00+08:00",
          "note": "欧洲时报记录巴黎市长称空调是「祸害」与大众疯抢空调的强烈反差，是梗传播的核心素材"
        }
      ]
    },
    {
      "id": "2026-06-27-wuxu-anhao",
      "title": "🌐 无需暗号，不用沟通",
      "aliases": [
        "全世界默契坑我",
        "被全世界针对",
        "无需暗号不用沟通默契联手"
      ],
      "platform": [
        "weibo",
        "other"
      ],
      "type": "句式梗",
      "summary": "世界杯韩国队因自身失利加上多组同日不利结果，球迷自嘲「无需暗号，不用沟通，全世界默契联手针对我们」——讽刺「感觉被全世界针对」本质上是自身问题的通用句式。",
      "origin": "2026年世界杯，韩国在平局即可出线的情况下0-1输南非，同日德国输厄瓜多尔、日本平瑞典、澳大利亚平巴拉圭，多项结果同日不利，韩国第三名排名跌至第六，出线危机。球迷在微博、腾讯社区以「全世界都在针对我韩」表达落寞，梗化为「无需暗号，不用沟通，大家默契做局」。微博热搜第7位（约30万热度），新浪、腾讯新闻详述。",
      "usage": "「无需暗号，不用沟通，[主体]默契联手[针对我]」——任何「感觉全世界合谋整我但其实是自身问题」的场景：无需暗号不用沟通，今天所有甲方默契地同时改需求；无需暗号不用沟通，所有快递默契选在我不在家时派件；延伸：「所有阴谋论的尽头，都是自己没考好」。",
      "fun_point": "精妙在于：真正的全球阴谋比这难协调，所以「无需暗号不用沟通」恰恰是在自嘲——世界根本没有针对你，只是你的失误引发了一连串正常反应。「感觉被全世界针对」是每个失败者的心理防御本能，把这瞬间做成句式，任何倒霉时刻都能套上去高度自洽。",
      "why_spread": "已验证：微博热搜第7位（约30万热度），新浪、腾讯新闻均有详述；推测：「感觉被全世界针对但其实是自己问题」是高频生活共鸣，世界杯顶流加持让梗快速出圈，「无需暗号不用沟通」结构整齐好记，可无限套入日常倒霉场景。",
      "lifecycle": "peak",
      "brand_usage": "职场/效率类可借「无需暗号，今天截止的任务同时堆来了」做打工人共鸣；互动话题：「你最近遇到过什么无需暗号的感觉」征集；UGC接龙：「无需暗号不用沟通，我今天的[倒霉遭遇]」。",
      "risk": {
        "level": "safe",
        "note": "体育幽默自嘲梗，不涉及政治内容；不点名任何运动员，聚焦「被全世界针对」的通用情绪模板。"
      },
      "score": 80,
      "days_on_list": 1,
      "published": true,
      "sources": [
        {
          "tier": "aggregator",
          "evidence_role": "popularity",
          "platform": "weibo",
          "url": "https://tophub.today/n/KqndgxeLl9",
          "title": "今日热榜·微博热搜",
          "captured_at": "2026-06-27T08:00:00+08:00",
          "note": "今日热榜微博热搜第7位「韩国队被全世界针对」约30万热度，全国级讨论热度确认"
        },
        {
          "tier": "search_media",
          "evidence_role": "origin",
          "platform": "other",
          "url": "https://www.sina.cn/news/detail/5314094228048808.html",
          "title": "韩国队被全世界针对",
          "captured_at": "2026-06-27T08:05:00+08:00",
          "note": "新浪收录世界杯韩国队同日遭遇多组不利结果，「全世界针对」叙事与「无需暗号不用沟通」梗化表达的传播起源"
        },
        {
          "tier": "search_media",
          "evidence_role": "usage_context",
          "platform": "other",
          "url": "https://news.qq.com/rain/a/20260626A08SY500",
          "title": "一天被「坑」三次！世界杯韩国队命运「失控」了",
          "captured_at": "2026-06-27T08:08:00+08:00",
          "note": "腾讯新闻详述韩国一天内三次被不利结果影响，记录球迷「默契针对论」与客观分析（韩国自身失误）的反差"
        }
      ]
    },
    {
      "id": "2026-06-27-xigai-lianxing",
      "title": "🦵 膝盖的大小居然和脸型一样",
      "aliases": [
        "无用身体冷知识",
        "XX居然和YY一样大",
        "身体比例触发自测"
      ],
      "platform": [
        "weibo",
        "other"
      ],
      "type": "其他",
      "summary": "「膝盖大小和脸型一样」等无用身体比例冷知识批量走红——「脚和小臂等长」「拳头≈心脏大小」「腰围=脖子×2」——触发「立刻自测」反应，衍生为「XX居然和YY一样大」的万能冷知识邀请模板。",
      "origin": "微博博主发布多条身体比例冷知识，「膝盖大小=脸型」因独特性登上热搜；相关节目中以膝盖测量道具尺寸的视频引发讨论；另有网友吐槽「一派胡言，谁家膝盖跟面盆一样大」形成调侃二创。微博热搜第20位（约8万热度），新浪收录正向传播与调侃反应。",
      "usage": "「你的XX居然和YY一样大/长」——任何令人无法相信但立刻可自测的身体或物理冷知识：你的手机高度居然和你的脸一样长；你的虎口居然能卡住你的脚踝；评论区接龙模板：「量了，果然，没用但开心了三秒」「这辈子知道了，但不知道用来干什么」。",
      "fun_point": "「无用知识增加了」的极致形态：量完之后你仍不知道这有什么用，但忍不住告诉旁边的人。「膝盖=脸型」让人第一反应「不可能」，第二反应「不行我得量量」，第三反应「量完了，确实，然后呢」——全程没有意义，但无比好玩，转发欲≈100%。",
      "why_spread": "已验证：微博热搜第20位（约8万热度），新浪收录正向传播与调侃反应两篇；推测：「无用冷知识+立刻可验证」是短视频天然高传播素材，验证门槛为零（当场量一下），分享欲接近满级，「试完告诉我结果」天然制造评论区互动。",
      "lifecycle": "rising",
      "brand_usage": "美容/美体类可借「膝盖透露你的脸型」做产品关联内容；科普类可做「关于你身体你不知道的N条冷知识」系列；互动话题：「量了告诉我，你的膝盖和脸型真的一样吗」——天然高评论转化率。",
      "risk": {
        "level": "safe",
        "note": "生理科普趣味梗，无争议；注意膝盖与脸型相关说法部分被调侃为夸张，使用时保持幽默调性，不作科学论断。"
      },
      "score": 75,
      "days_on_list": 1,
      "published": true,
      "sources": [
        {
          "tier": "aggregator",
          "evidence_role": "popularity",
          "platform": "weibo",
          "url": "https://tophub.today/n/KqndgxeLl9",
          "title": "今日热榜·微博热搜",
          "captured_at": "2026-06-27T08:00:00+08:00",
          "note": "今日热榜微博热搜第20位「膝盖的大小居然和脸型一样」约8万热度在榜，确认话题在Weibo的传播热度"
        },
        {
          "tier": "search_media",
          "evidence_role": "origin",
          "platform": "other",
          "url": "https://www.sina.cn/news/detail/5314204359202247.html",
          "title": "身体冷知识你知道？",
          "captured_at": "2026-06-27T08:05:00+08:00",
          "note": "新浪收录「膝盖大小=脸型」等多条身体比例冷知识原始帖，含脚=小臂、拳头=心脏等同源自测触发内容"
        },
        {
          "tier": "search_media",
          "evidence_role": "usage_context",
          "platform": "other",
          "url": "https://www.sina.cn/news/detail/5314237901571493.html",
          "title": "膝盖大小和脸型一样是胡言",
          "captured_at": "2026-06-27T08:08:00+08:00",
          "note": "新浪调侃回应「一派胡言，谁家膝盖跟面盆一样大」，记录话题引发的质疑→自测→调侃的二创传播路径"
        }
      ]
    },
    {
      "id": "2026-06-27-bad-review-guilt",
      "title": "⭐ 我打差评不是为了让店员丢工作",
      "aliases": [
        "差评内疚困境",
        "消费者道德悖论",
        "打差评又心软"
      ],
      "platform": [
        "weibo",
        "other"
      ],
      "type": "情绪梗",
      "summary": "「打差评可能导致店员丢工作」的道德愧疚困境成为新热梗——消费者的正当维权与对普通员工的共情产生撕裂，「我打差评不是为了让他/她丢工作」成为一句话说清楚「善意消费者的两难」的通用表达。",
      "origin": "微博幽默博主6月26日发布系列图文，以轻松方式表达差评者的道德两难；话题背景有奢侈品店员讽刺顾客「穷逛」后遭开除与行业拉黑的事件，引发对「差评→失业连锁」的广泛讨论。微博热搜第32位（约6万热度），新浪收录幽默帖，搜狐记录事件背景。",
      "usage": "「我[行为]不是为了让[对方][承担后果]，但是……」——任何「合理维权却担心波及无辜」的内疚困境：我投诉不是为了让客服受气，但产品真的不行；我说实话不是为了让你哭，但你问我了；延伸：「每一个差评背后，都有一个觉得自己不是坏人的消费者」。",
      "fun_point": "「消费者的正当权利」和「普通人的共情能力」之间永恒的拉锯。打差评本是消费者保护机制，但「担心店员因此丢工作」让维权变成了愧疚体验。这个梗把人人心里有但从没说出口的内疚感说出来——让人一看就「你懂我」，是情绪代言型梗的标准形态。",
      "why_spread": "已验证：微博热搜第32位（约6万热度），新浪收录幽默图文，搜狐记录奢侈品店员讽刺顾客被开除背景事件；推测：消费投诉是高频场景，「权利vs共情」道德困境人人经历过，句式简洁直接套用，自嘲属性让分享门槛极低。",
      "lifecycle": "rising",
      "brand_usage": "客服/售后平台可借「让每个反馈都有价值，不让任何人因此承受无辜代价」做服务承诺；内容账号可做「你最难开口打的差评是什么」互动；职场心理安全类：「说出问题的人，不是坏人」。",
      "risk": {
        "level": "low",
        "note": "消费伦理话题有双面解读，可能被误读为为差评骚扰洗白；使用时聚焦善意消费者的真实困惑，不鼓励恶意差评。"
      },
      "score": 72,
      "days_on_list": 1,
      "published": true,
      "sources": [
        {
          "tier": "aggregator",
          "evidence_role": "popularity",
          "platform": "weibo",
          "url": "https://tophub.today/n/KqndgxeLl9",
          "title": "今日热榜·微博热搜",
          "captured_at": "2026-06-27T08:00:00+08:00",
          "note": "今日热榜微博热搜第32位「我打差评不是为了让店员丢工作」约6万热度在榜，确认话题在Weibo传播"
        },
        {
          "tier": "search_media",
          "evidence_role": "origin",
          "platform": "other",
          "url": "https://www.sina.cn/news/detail/5314074539724857.html",
          "title": "我打差评不为丢工作",
          "captured_at": "2026-06-27T08:05:00+08:00",
          "note": "新浪收录幽默图文，记录差评者内疚情绪的梗化表达及评论区「懂」的共鸣反应，确认传播起点"
        },
        {
          "tier": "search_media",
          "evidence_role": "usage_context",
          "platform": "other",
          "url": "https://www.sohu.com/a/1031432961_122158072",
          "title": "店员讽刺顾客「穷逛」后续：脸丢光了，工作没了，商场惨遭牵连",
          "captured_at": "2026-06-27T08:08:00+08:00",
          "note": "搜狐记录奢侈品店员轻视顾客后被开除事件，提供「差评→失业」链条的现实背景，解释梗兴起的社会语境"
        }
      ]
    },
    {
      "id": "2026-06-27-wang-bu-jian-wang",
      "title": "🏆 王不见王",
      "aliases": [
        "两王错位",
        "顶流双雄错峰",
        "命运安排的错过"
      ],
      "platform": [
        "weibo",
        "other"
      ],
      "type": "句式梗",
      "summary": "世界杯万众期待的顶级双雄对决，因一方战略性坐板凳而落空——「王不见王」成为「最期待的双雄相遇，因时机/策略/命运阴差阳错未能正面交锋」的通用遗憾叙事模板。",
      "origin": "世界杯I组第三轮法挪大战开赛前，挪威宣布战略性轮替核心射手替补出场，法国阵中顶级射手先发；备受期待的双核正面对决未能实现，全网热议「这届世界杯最遗憾的错过」。微博热搜第2位（约67万热度），新浪体育确认阵容安排。「王不见王」出自中国象棋将帅不能对面的规则。",
      "usage": "「王不见王」——任何「原本万众期待的两大顶流同场竞技，却因各种原因没有正面交锋」：两个行业最强的人进了同一公司，但一个早就离职了，王不见王；论坛两大神仙约架互怼，发完文却没有互相回应，王不见王；两个卷王进了同一个项目，但一个调岗了，王不见王。",
      "fun_point": "「王不见王」出自中国象棋（将帅不能直接对面），被套进来就有了命运弄人的古典戏剧感。最强的两个人不是打不过对方，而是「根本没有在同一时空里真正相遇」——这比失败更令人叹息。「命运安排他们永远错位一步」才是最深的遗憾梗，适合任何行业双雄叙事。",
      "why_spread": "已验证：微博热搜第2位（约67万热度），新浪体育详述阵容轮替导致双雄错位的赛前报道；推测：世界杯顶流加持，「遗憾没有相遇」比「相遇后分出胜负」更有故事性，「王不见王」四字简洁典雅，适合套进任何行业或生活的双雄错位叙事。",
      "lifecycle": "peak",
      "brand_usage": "高端/奢侈品牌可借「王者相遇，各有风骨」做品牌气质文案；赛事/对决活动可用「本届终于王见王」；内容账号可征集「你见证过最遗憾的王不见王是哪次」故事；职场类：「一山容得下两个王，前提是他们在同一个项目组」。",
      "risk": {
        "level": "safe",
        "note": "文化典故套用，无争议；不涉及具体运动员名称，不评判赛事胜负，聚焦「遗憾错位」情绪叙事。"
      },
      "score": 78,
      "days_on_list": 1,
      "published": true,
      "sources": [
        {
          "tier": "aggregator",
          "evidence_role": "popularity",
          "platform": "weibo",
          "url": "https://tophub.today/n/KqndgxeLl9",
          "title": "今日热榜·微博热搜",
          "captured_at": "2026-06-27T08:00:00+08:00",
          "note": "今日热榜微博热搜第2位（约67万热度），世界杯I组顶级双雄王不见王话题，确认全国顶流讨论热度"
        },
        {
          "tier": "search_media",
          "evidence_role": "origin",
          "platform": "other",
          "url": "https://news.sina.com.cn/zx/2026-06-27/doc-inieuimk5088425.shtml",
          "title": "世界杯-挪威vs法国首发：姆巴佩先发哈兰德替补！登贝莱出战",
          "captured_at": "2026-06-27T08:05:00+08:00",
          "note": "新浪体育确认赛前阵容：挪威核心射手替补，法国核心先发，双雄未能同场对决，「王不见王」背景确认"
        }
      ]
    },
    {
      "id": "2026-06-27-phone-seismograph",
      "title": "📱 手机计步器其实是个隐形地震仪",
      "aliases": [
        "你的手机在监测地震",
        "XX其实是个隐形YY",
        "手机双重身份"
      ],
      "platform": [
        "weibo",
        "other"
      ],
      "type": "其他",
      "summary": "一天内全球四场强震触发科普：你手机里的计步器加速度传感器早已用于全球地震预警网络——「XX其实是个隐形YY」的隐藏身份发现感，成为「原来我一直拥有某功能却不知道」的惊觉梗模板。",
      "origin": "2026年6月26日一天内发生四场强震（日本6.9级、委内瑞拉7.5级、加州5.6级、印尼6.8级）。有博主指出：手机加速度传感器（即计步器底层硬件）已被用于全球地震预警体系，手机在后台持续监测加速度异常。国内智能手机已部署此技术（曾有手机平台误触发预警引发广泛关注）。百度实时热搜第17位（约638万热度）。",
      "usage": "「你以为的XX，其实是个隐形YY」——任何「平凡设备/功能的隐藏超能力」：你以为的冰箱，其实是个隐形温控传感器；你以为的手表，其实是个隐形心电图；延伸：「我的[平凡物品]居然一直在默默[超预期功能]」；品牌文案：「你不知道，但我们一直在做」。",
      "fun_point": "「默默做了大事却从不提」的反差感：你以为计步器在数你今天走了多少步，其实它顺手做了地震监测。当日四场地震同天发生，让这条知识「今天特别有用」——让人忍不住掏出手机看「我的手机今天有没有检测到地震」，验证欲极强。",
      "why_spread": "已验证：百度实时热搜第17位（约638万热度），四场大地震同日触发关注；国内手机平台已落地地震预警功能有实际案例可印证；推测：「熟悉设备的隐藏功能」是强互动话题，「原来我一直拥有这个功能」触发分享欲，四震同日的新闻背景让知识科普到来得恰到好处。",
      "lifecycle": "peak",
      "brand_usage": "手机品牌可借「你的手机，一直在背后守护更多」做安全感文案；科技产品普遍可用「你以为的XX，其实是个隐形YY」揭秘隐藏功能；内容账号可做「你身边那些被低估的科技守护者」盘点系列；地震/应急类机构可借势普及地震预警知识。",
      "risk": {
        "level": "low",
        "note": "科技科普梗，注意避免暗示手机监控隐私；着重「为公共安全贡献」正向叙事，不夸大手机地震监测精度。"
      },
      "score": 79,
      "days_on_list": 1,
      "published": true,
      "sources": [
        {
          "tier": "aggregator",
          "evidence_role": "popularity",
          "platform": "other",
          "url": "https://top.baidu.com/board?tab=realtime",
          "title": "百度热搜实时榜",
          "captured_at": "2026-06-27T08:00:00+08:00",
          "note": "百度实时热搜第17位「手机计步器其实是个隐形地震仪」（约638万热度），四震同日背景下科普话题全国级爆发"
        },
        {
          "tier": "search_media",
          "evidence_role": "usage_context",
          "platform": "other",
          "url": "https://cj.sina.com.cn/articles/view/7879848900/1d5acf3c406802zjjc",
          "title": "小米公司对于此次地震预警误报事件给出了什么解释？",
          "captured_at": "2026-06-27T08:10:00+08:00",
          "note": "新浪财经记录国内手机平台地震预警误报事件，确认智能手机已实际部署加速度传感器地震监测技术，为梗的技术背景提供实证"
        }
      ]
    }
  ],
  "published_at": "2026-06-27T07:31:15+08:00"
}
